mlcommons_box_docker/__init__.py
mlcommons_box_docker/__main__.py
mlcommons_box_docker/docker_run.py
mlcommons_box_docker/tests/__init__.py
mlcommons_box_docker/tests/test_mlcommons_box_docker_cli.py
mlcommons_box_docker-0.2.3.dist-info/METADATA
mlcommons_box_docker-0.2.3.dist-info/WHEEL
mlcommons_box_docker-0.2.3.dist-info/entry_points.txt
mlcommons_box_docker-0.2.3.dist-info/top_level.txt
mlcommons_box_docker-0.2.3.dist-info/RECORD
