Metadata-Version: 2.1
Name: mlcommons-box-docker
Version: 0.2.3
Summary: UNKNOWN
Home-page: UNKNOWN
License: Apache 2.0
Platform: UNKNOWN
Requires-Python: >=3.6
Requires-Dist: click (==7.1.2)
Requires-Dist: mlspeclib (==1.0.0)
Requires-Dist: mlcommons-box (==0.2.3)
